noalchemy/__init__.py
noalchemy/engine.py
noalchemy/version.py
noalchemy/exc/__init__.py
noalchemy/odm/__init__.py
noalchemy/odm/aggregation.py
noalchemy/odm/document.py
noalchemy/odm/models.py
noalchemy/odm/query.py
noalchemy/odm/relationship.py
noalchemy/odm/session.py
noalchemy/odm/transaction.py
noalchemy/types/Dict.py
noalchemy/types/Integer.py
noalchemy/types/Key.py
noalchemy/types/List.py
noalchemy/types/String.py
noalchemy/types/__init__.py
tests/__init__.py
tests/test_1_version.py
tests/test_2_engine.py
tests/test_3_database.py
NoAlchemy-0.2.2.dist-info/LICENSE
NoAlchemy-0.2.2.dist-info/METADATA
NoAlchemy-0.2.2.dist-info/WHEEL
NoAlchemy-0.2.2.dist-info/top_level.txt
NoAlchemy-0.2.2.dist-info/RECORD
