Metadata-Version: 2.1
Name: NoAlchemy
Version: 0.2.2
Summary: A MongoDB Object-Document Mapper (ODM) based on SQLAlchemy.
Home-page: https://github.com/grantUser/NoAlchemy
Author: grantUser
Maintainer: grantUser
License: MIT
Keywords: MongoDB,Object-Document Mapper,ODM,SQLAlchemy
Classifier: Development Status :: 5 - Production/Stable
Classifier: Intended Audience :: Developers
Classifier: License :: OSI Approved :: MIT License
Classifier: Programming Language :: Python :: 3.8
Classifier: Programming Language :: Python :: 3.9
Classifier: Programming Language :: Python :: 3.10
Classifier: Topic :: Database
Classifier: Topic :: Software Development :: Libraries :: Python Modules
Requires-Python: >=3.8, <4
License-File: LICENSE
Requires-Dist: pymongo
Requires-Dist: mongomock
Requires-Dist: pytest
